ownerrezconnector/__init__.py
ownerrezconnector/api.py
ownerrezconnector/constants.py
ownerrezconnector/exeptions.py
ownerrezconnector/model.py
ownerrezconnector/model2.py
ownerrezconnector/restAdapter.py
ownerrezconnector/test/__init__.py
ownerrezconnector/test/context.py
ownerrezconnector/test/tests.py
ownerrezapiwrapper-0.0.8.dist-info/LICENSE
ownerrezapiwrapper-0.0.8.dist-info/METADATA
ownerrezapiwrapper-0.0.8.dist-info/WHEEL
ownerrezapiwrapper-0.0.8.dist-info/top_level.txt
ownerrezapiwrapper-0.0.8.dist-info/zip-safe
ownerrezapiwrapper-0.0.8.dist-info/RECORD
